imgram/__init__.py
imgram/imgram.py
imgram-1.0.1.dist-info/entry_points.txt
imgram-1.0.1.dist-info/licenses/LICENSE
imgram-1.0.1.dist-info/WHEEL
imgram-1.0.1.dist-info/METADATA
imgram-1.0.1.dist-info/RECORD
