Metadata-Version: 2.4
Name: imgram
Version: 1.0.1
Summary: Instagram media downloader CLI (doesn't work for stories)
Keywords: Instagram,IG,Instagram download,download,instagram post,social media
Author: Doozy
Requires-Python: >=3.11
License-Expression: MIT
Classifier: Programming Language :: Python :: 3
Classifier: Operating System :: OS Independent
Classifier: Development Status :: 5 - Production/Stable
License-File: LICENSE
Requires-Dist: click>=8.1
Requires-Dist: instagrapi
Requires-Dist: pwinput
Project-URL: Homepage, https://github.com/d00zylive/Imgram/tree/master
Project-URL: Issues, https://github.com/d00zylive/Imgram/issues
Project-URL: Repository, https://github.com/d00zylive/Imgram.git
